yowasp_wavedrom/__init__.py
yowasp_wavedrom/bundle.js
yowasp_wavedrom-3.5.0.8.dist-info/METADATA
yowasp_wavedrom-3.5.0.8.dist-info/WHEEL
yowasp_wavedrom-3.5.0.8.dist-info/entry_points.txt
yowasp_wavedrom-3.5.0.8.dist-info/top_level.txt
yowasp_wavedrom-3.5.0.8.dist-info/RECORD
