Metadata-Version: 2.1
Name: yowasp-wavedrom
Version: 3.5.0.8
Summary: WaveDrom generates diagrams for digital waveforms, bit fields, and simple combinational circuits
Author-email: Catherine <whitequark@whitequark.org>
License: MIT
Project-URL: Homepage, https://yowasp.org/
Project-URL: Source Code, https://github.com/YoWASP/wavedrom
Project-URL: Bug Tracker, https://github.com/YoWASP/wavedrom/issues
Classifier: License :: OSI Approved :: MIT License
Requires-Python: ~=3.8
Requires-Dist: quickjs ~=1.19
Requires-Dist: importlib-resources ; python_version < "3.9"
